pycounts_merete/__init__.py
pycounts_merete/plotting.py
pycounts_merete/pycounts_merete.py
pycounts_merete-0.1.1.dist-info/LICENSE
pycounts_merete-0.1.1.dist-info/METADATA
pycounts_merete-0.1.1.dist-info/WHEEL
pycounts_merete-0.1.1.dist-info/RECORD
